crfmnes/__init__.py
crfmnes/alg.py
crfmnes-1.0.0.dist-info/LICENSE
crfmnes-1.0.0.dist-info/METADATA
crfmnes-1.0.0.dist-info/WHEEL
crfmnes-1.0.0.dist-info/top_level.txt
crfmnes-1.0.0.dist-info/RECORD
